dnpr/__init__.py
dnpr/clsDnpr.py
dnpr/setup.py
Dnpr-0.1.0.post1.dist-info/LICENSE
Dnpr-0.1.0.post1.dist-info/METADATA
Dnpr-0.1.0.post1.dist-info/WHEEL
Dnpr-0.1.0.post1.dist-info/top_level.txt
Dnpr-0.1.0.post1.dist-info/RECORD
