Metadata-Version: 2.1
Name: Dnpr
Version: 0.1.0.post1
Summary: Useful Data manipulation functions for JSON. Fixed partition by bug.
Home-page: https://github.com/SatyakiDe2019/Dnpr
Author: Satyaki De
Author-email: satyaki.de@gmail.com
License: UNKNOWN
Platform: UNKNOWN
Classifier: Programming Language :: Python :: 3
Classifier: License :: OSI Approved :: MIT License
Classifier: Operating System :: OS Independent
Requires-Dist: markdown
Requires-Dist: pandas
Requires-Dist: regex
